<?xml version="1.0" encoding="UTF-8"?>
<mods xmlns="http://www.loc.gov/mods/v3" xmlns:xlink="http://www.w3.org/1999/xlink" xmlns:xsi="http://www.w3.org/2001/XMLSchema-instance" version="3.5" xsi:schemaLocation="http://www.loc.gov/mods/v3 http://www.loc.gov/standards/mods/v3/mods-3-5.xsd">
<titleInfo><title>Stoneware Sculptural Arc - part peeler_1</title></titleInfo><name><namePart>Richard Peeler</namePart><role><roleTerm>Creator</roleTerm></role></name><originInfo><dateCreated>1977</dateCreated></originInfo><physicalDescription><extent>13 1/4" x 15 1/2" x 3 1/2"</extent></physicalDescription><abstract>handbuilt stoneware</abstract><identifier type="filename">Peeler_rotate.mov</identifier><accessCondition type="use and reproduction" xlink:href="http://rightsstatements.org/vocab/CNE/1.0/">Copyright Not Evaluated</accessCondition><recordInfo><recordContentSource valueURI="http://id.loc.gov/authorities/names/n87808088">University of Tennessee, Knoxville. Libraries</recordContentSource></recordInfo><typeOfResource>still image</typeOfResource></mods>